.editorconfig
.gitattributes
.gitignore
.mailmap
.packit.yml
.travis.yml
AUTHORS
COPYING
HACKING.md
LICENSE
MANIFEST.in
README.md
history.md
man.asciidoc
mkdocs.yml
pylintrc
releasers.conf.5.asciidoc
requirements.txt
runtests.py
setup.py
tito
tito.8.asciidoc
tito.jpg
tito.props.5.asciidoc
tito.spec
titorc.5.asciidoc
tox.ini
wercker.yml
.github/workflows/fedora-tox.yml
.github/workflows/python-diff-lint.yml
.github/workflows/shell-diff-lint.yml
.tito/releasers.conf
.tito/tito.props
.tito/custom/custom.py
.tito/packages/tito
.tito/templates/__init__.py.tpl
bin/generate-patches.pl
doc/builders.md
doc/index.md
doc/maintenance.md
doc/mead.md
hacking/runtests.sh
hacking/titotest-centos-6/Dockerfile
hacking/titotest-centos-7/Dockerfile
hacking/titotest-fedora-33/Dockerfile
hacking/titotest-fedora-rawhide/Dockerfile
share/tito_completion.sh
src/tito/__init__.py
src/tito/bugtracker.py
src/tito/buildparser.py
src/tito/cli.py
src/tito/common.py
src/tito/compat.py
src/tito/config_object.py
src/tito/distributionbuilder.py
src/tito/exception.py
src/tito/tar.py
src/tito.egg-info/PKG-INFO
src/tito.egg-info/SOURCES.txt
src/tito.egg-info/dependency_links.txt
src/tito.egg-info/entry_points.txt
src/tito.egg-info/requires.txt
src/tito.egg-info/top_level.txt
src/tito/builder/__init__.py
src/tito/builder/fetch.py
src/tito/builder/main.py
src/tito/builder/submodule_aware_builder.py
src/tito/release/__init__.py
src/tito/release/copr.py
src/tito/release/distgit.py
src/tito/release/main.py
src/tito/release/obs.py
src/tito/tagger/__init__.py
src/tito/tagger/cargobump.py
src/tito/tagger/main.py
src/tito/tagger/rheltagger.py
src/tito/tagger/susetagger.py
src/tito/tagger/zstreamtagger.py
test/functional/__init__.py
test/functional/build_gitannex_tests.py
test/functional/build_tito_tests.py
test/functional/builder_tests.py
test/functional/cargo_tag_tests.py
test/functional/custom_tag_tests.py
test/functional/fetch_tests.py
test/functional/fixture.py
test/functional/multiproject_tests.py
test/functional/release_copr_tests.py
test/functional/release_yum_tests.py
test/functional/singleproject_tests.py
test/functional/specs/extsrc-2.spec
test/functional/specs/extsrc-3.spec
